uipath_connectors/microsoft_outlook365/__init__.py
uipath_connectors/microsoft_outlook365/client.py
uipath_connectors/microsoft_outlook365/errors.py
uipath_connectors/microsoft_outlook365/py.typed
uipath_connectors/microsoft_outlook365/types.py
uipath_connectors/microsoft_outlook365/api/__init__.py
uipath_connectors/microsoft_outlook365/api/archive_email/__init__.py
uipath_connectors/microsoft_outlook365/api/archive_email/archive_email.py
uipath_connectors/microsoft_outlook365/api/calendar/__init__.py
uipath_connectors/microsoft_outlook365/api/calendar/get_event_by_id.py
uipath_connectors/microsoft_outlook365/api/calendars/__init__.py
uipath_connectors/microsoft_outlook365/api/calendars/get_calendars.py
uipath_connectors/microsoft_outlook365/api/create_event/__init__.py
uipath_connectors/microsoft_outlook365/api/create_event/create_event_v2.py
uipath_connectors/microsoft_outlook365/api/delete_event/__init__.py
uipath_connectors/microsoft_outlook365/api/delete_event/delete_event.py
uipath_connectors/microsoft_outlook365/api/download_attachment/__init__.py
uipath_connectors/microsoft_outlook365/api/download_attachment/download_attachment.py
uipath_connectors/microsoft_outlook365/api/download_email/__init__.py
uipath_connectors/microsoft_outlook365/api/download_email/download_email.py
uipath_connectors/microsoft_outlook365/api/forward_email_v2/__init__.py
uipath_connectors/microsoft_outlook365/api/forward_email_v2/forward_email_v2.py
uipath_connectors/microsoft_outlook365/api/forward_event/__init__.py
uipath_connectors/microsoft_outlook365/api/forward_event/forward_event.py
uipath_connectors/microsoft_outlook365/api/get_event_list/__init__.py
uipath_connectors/microsoft_outlook365/api/get_event_list/get_event_list.py
uipath_connectors/microsoft_outlook365/api/get_newest_email/__init__.py
uipath_connectors/microsoft_outlook365/api/get_newest_email/get_newest_email.py
uipath_connectors/microsoft_outlook365/api/list_emails/__init__.py
uipath_connectors_microsoft_outlook365-1.32.3.dev12.dist-info/METADATA
uipath_connectors_microsoft_outlook365-1.32.3.dev12.dist-info/WHEEL
uipath_connectors_microsoft_outlook365-1.32.3.dev12.dist-info/entry_points.txt
uipath_connectors_microsoft_outlook365-1.32.3.dev12.dist-info/top_level.txt
uipath_connectors_microsoft_outlook365-1.32.3.dev12.dist-info/RECORD
